bip/__init__.py
bip/__version__.py
bip/app.py
bip/config.py
bip/config_test.py
bip/display.py
bip/ext.py
bip/models.py
bip/search.py
bip/wsgi.py
bip/admin/__init__.py
bip/admin/forms.py
bip/admin/utils.py
bip/admin/views.py
bip/admin/templates/admin/attachment_detail.html
bip/admin/templates/admin/attachment_list.html
bip/admin/templates/admin/base.html
bip/admin/templates/admin/index.html
bip/admin/templates/admin/label_detail.html
bip/admin/templates/admin/label_list.html
bip/admin/templates/admin/page_attachments.html
bip/admin/templates/admin/page_detail.html
bip/admin/templates/admin/page_labels.html
bip/admin/templates/admin/page_list.html
bip/admin/templates/admin/user_detail.html
bip/admin/templates/admin/user_list.html
bip/auth/__init__.py
bip/auth/forms.py
bip/auth/views.py
bip/auth/templates/auth/base.html
bip/auth/templates/auth/login.html
bip/cli/__init__.py
bip/cli/attachments/__init__.py
bip/cli/attachments/commands.py
bip/cli/database/__init__.py
bip/cli/database/commands.py
bip/cli/pages/__init__.py
bip/cli/pages/commands.py
bip/cli/users/__init__.py
bip/cli/users/commands.py
bip/main/__init__.py
bip/main/forms.py
bip/main/templates.py
bip/main/utils.py
bip/main/views.py
bip/main/templates/main/base.html
bip/main/templates/main/basic_information.html
bip/main/templates/main/changes.html
bip/main/templates/main/contact.html
bip/main/templates/main/index.html
bip/main/templates/main/label_page_list.html
bip/main/templates/main/page.html
bip/main/templates/main/search.html
bip/main/templates/main/staff.html
bip/static/robots.txt
bip/static/css/app.css
bip/static/img/bip.svg
bip/static/img/icon.png
bip/static/img/logo.svg
bip/static/vendor/easymde.min.css
bip/static/vendor/easymde.min.js
bip/static/vendor/jquery-3.5.1.slim.js
bip/static/vendor/jquery-3.5.1.slim.min.js
bip/static/vendor/jquery-3.5.1.slim.min.map
bip/static/vendor/popper.js
bip/static/vendor/popper.js.map
bip/static/vendor/popper.min.js
bip/static/vendor/popper.min.js.map
biuletyn_bip-0.7.1.dist-info/LICENSE
biuletyn_bip-0.7.1.dist-info/METADATA
biuletyn_bip-0.7.1.dist-info/WHEEL
biuletyn_bip-0.7.1.dist-info/entry_points.txt
biuletyn_bip-0.7.1.dist-info/top_level.txt
biuletyn_bip-0.7.1.dist-info/RECORD
