Metadata-Version: 2.1
Name: biuletyn-bip
Version: 0.7.1
Summary: Polish BIP (Biuletyn Informacji Publicznej) as Flask application
Home-page: https://github.com/zgoda/bip
Author: Jarek Zgoda
Author-email: jarek.zgoda@gmail.com
License: GPLv3
Project-URL: Documentation, https://bip.readthedocs.io/
Project-URL: Source, https://github.com/zgoda/bip
Project-URL: Issues, https://github.com/zgoda/bip/issues
Keywords: bip public information bulletin
Platform: UNKNOWN
Classifier: Development Status :: 4 - Beta
Classifier: Environment :: Web Environment
Classifier: Framework :: Flask
Classifier: License :: OSI Approved :: GNU General Public License v3 (GPLv3)
Classifier: Natural Language :: Polish
Classifier: Operating System :: POSIX :: Linux
Classifier: Programming Language :: Python :: 3 :: Only
Classifier: Programming Language :: Python :: 3.7
Classifier: Programming Language :: Python :: 3.8
Classifier: Topic :: Internet :: WWW/HTTP :: Dynamic Content :: Content Management System
Requires-Python: ~=3.7
Requires-Dist: Flask (<2)
Requires-Dist: Jinja2 (<3)
Requires-Dist: MarkupSafe (<2)
Requires-Dist: itsdangerous (<2)
Requires-Dist: PeeWee
Requires-Dist: Flask-Login
Requires-Dist: WTForms (>2.3.2)
Requires-Dist: Flask-WTF
Requires-Dist: Flask-Babel
Requires-Dist: Bootstrap-Flask
Requires-Dist: sentry-sdk[flask]
Requires-Dist: validators
Requires-Dist: Werkzeug
Requires-Dist: markdown
Requires-Dist: python-dotenv
Requires-Dist: text-unidecode
Requires-Dist: Click
Requires-Dist: keyring
Requires-Dist: keyrings.cryptfile
Requires-Dist: texttable
Requires-Dist: python-magic
Provides-Extra: dev
Requires-Dist: ipython ; extra == 'dev'
Requires-Dist: ipdb ; extra == 'dev'
Requires-Dist: pip ; extra == 'dev'
Requires-Dist: setuptools ; extra == 'dev'
Requires-Dist: wheel ; extra == 'dev'
Requires-Dist: flake8 ; extra == 'dev'
Requires-Dist: flake8-builtins ; extra == 'dev'
Requires-Dist: flake8-bugbear ; extra == 'dev'
Requires-Dist: flake8-mutable ; extra == 'dev'
Requires-Dist: flake8-comprehensions ; extra == 'dev'
Requires-Dist: pep8-naming ; extra == 'dev'
Requires-Dist: dlint ; extra == 'dev'
Requires-Dist: rstcheck ; extra == 'dev'
Requires-Dist: rope ; extra == 'dev'
Requires-Dist: isort ; extra == 'dev'
Requires-Dist: flask-shell-ipython ; extra == 'dev'
Requires-Dist: watchdog ; extra == 'dev'
Requires-Dist: pytest ; extra == 'dev'
Requires-Dist: pytest-mock ; extra == 'dev'
Requires-Dist: pytest-cov ; extra == 'dev'
Requires-Dist: pytest-factoryboy ; extra == 'dev'
Requires-Dist: pytest-flask ; extra == 'dev'
Requires-Dist: Sphinx ; extra == 'dev'
Provides-Extra: docs
Requires-Dist: Sphinx ; extra == 'docs'
Provides-Extra: test
Requires-Dist: pytest ; extra == 'test'
Requires-Dist: pytest-mock ; extra == 'test'
Requires-Dist: pytest-cov ; extra == 'test'
Requires-Dist: pytest-factoryboy ; extra == 'test'
Requires-Dist: pytest-flask ; extra == 'test'
